{
	"format_version": "1.8.0",
	"animations": {
		"animation": {
			"loop": "hold_on_last_frame",
			"animation_length": 12,
			"bones": {
				"bone6": {
					"position": {
						"0.0": {
							"vector": [0, 0, 0]
						},
						"2.0": {
							"vector": [41, 11, 0]
						},
						"10.0": {
							"vector": [41, 11, 0]
						},
						"12.0": {
							"vector": [0, 0, 0]
						}
					}
				},
				"bone7": {
					"position": {
						"0.0": {
							"vector": [0, 0, 0]
						},
						"1.0": {
							"vector": [0, 0, 0]
						},
						"2.0": {
							"vector": [-13, 0, 13]
						},
						"10.0": {
							"vector": [-13, 0, 13]
						},
						"11.0": {
							"vector": [0, 0, 0]
						},
						"12.0": {
							"vector": [0, 0, 0]
						}
					}
				},
				"bone8": {
					"position": {
						"0.0": {
							"vector": [0, 0, 0]
						},
						"1.0": {
							"vector": [0, 0, 0]
						},
						"2.0": {
							"vector": [-13, 0, -13]
						},
						"10.0": {
							"vector": [-13, 0, -13]
						},
						"11.0": {
							"vector": [0, 0, 0]
						},
						"12.0": {
							"vector": [0, 0, 0]
						}
					}
				},
				"bone9": {
					"position": {
						"0.0": {
							"vector": [0, 0, 0]
						},
						"1.0": {
							"vector": [0, 0, 0]
						},
						"2.0": {
							"vector": [13, 0, -13]
						},
						"10.0": {
							"vector": [13, 0, -13]
						},
						"11.0": {
							"vector": [0, 0, 0]
						},
						"12.0": {
							"vector": [0, 0, 0]
						}
					}
				},
				"bone10": {
					"position": {
						"0.0": {
							"vector": [0, 0, 0]
						},
						"1.0": {
							"vector": [0, 0, 0]
						},
						"2.0": {
							"vector": [13, 0, 13]
						},
						"10.0": {
							"vector": [13, 0, 13]
						},
						"11.0": {
							"vector": [0, 0, 0]
						},
						"12.0": {
							"vector": [0, 0, 0]
						}
					}
				},
				"bone11": {
					"position": {
						"0.0": {
							"vector": [0, 0, 0]
						},
						"1.0": {
							"vector": [0, 0, 0]
						},
						"2.0": {
							"vector": [-13, 0, 13]
						},
						"10.0": {
							"vector": [-13, 0, 13]
						},
						"11.0": {
							"vector": [0, 0, 0]
						},
						"12.0": {
							"vector": [0, 0, 0]
						}
					}
				},
				"bone12": {
					"position": {
						"0.0": {
							"vector": [0, 0, 0]
						},
						"1.0": {
							"vector": [0, 0, 0]
						},
						"2.0": {
							"vector": [-13, 0, -13]
						},
						"10.0": {
							"vector": [-13, 0, -13]
						},
						"11.0": {
							"vector": [0, 0, 0]
						},
						"12.0": {
							"vector": [0, 0, 0]
						}
					}
				},
				"bone13": {
					"position": {
						"0.0": {
							"vector": [0, 0, 0]
						},
						"1.0": {
							"vector": [0, 0, 0]
						},
						"2.0": {
							"vector": [13, 0, -13]
						},
						"10.0": {
							"vector": [13, 0, -13]
						},
						"11.0": {
							"vector": [0, 0, 0]
						},
						"12.0": {
							"vector": [0, 0, 0]
						}
					}
				},
				"bone14": {
					"position": {
						"0.0": {
							"vector": [0, 0, 0]
						},
						"1.0": {
							"vector": [0, 0, 0]
						},
						"2.0": {
							"vector": [13, 0, 13]
						},
						"10.0": {
							"vector": [13, 0, 13]
						},
						"11.0": {
							"vector": [0, 0, 0]
						},
						"12.0": {
							"vector": [0, 0, 0]
						}
					}
				},
				"bone15": {
					"position": {
						"0.0": {
							"vector": [0, 0, 0]
						},
						"1.0": {
							"vector": [0, 0, 0]
						},
						"2.0": {
							"vector": [0, 10, 0]
						},
						"10.0": {
							"vector": [0, 10, 0]
						},
						"11.0": {
							"vector": [0, 0, 0]
						},
						"12.0": {
							"vector": [0, 0, 0]
						}
					}
				},
				"bone16": {
					"position": {
						"0.0": {
							"vector": [0, 0, 0]
						},
						"2.0": {
							"vector": [0, -10, 0]
						},
						"10.0": {
							"vector": [0, -10, 0]
						},
						"12.0": {
							"vector": [0, 0, 0]
						}
					}
				}
			}
		}
	}
}